mclabs/__init__.py
mclabs/google_maps_mcp_server/__init__.py
mclabs/google_maps_mcp_server/server.py
mclabs_google_maps_mcp_server-0.1.0.dist-info/METADATA
mclabs_google_maps_mcp_server-0.1.0.dist-info/WHEEL
mclabs_google_maps_mcp_server-0.1.0.dist-info/entry_points.txt
mclabs_google_maps_mcp_server-0.1.0.dist-info/RECORD
