Metadata-Version: 2.4
Name: mclabs.google_maps_mcp_server
Version: 0.1.0
Summary: Google Maps MCP Server using FastMCP framework
Project-URL: Homepage, https://github.com/lesonky/google-maps-mcp
Project-URL: Repository, https://github.com/lesonky/google-maps-mcp
Project-URL: Documentation, https://github.com/lesonky/google-maps-mcp#readme
Project-URL: Issues, https://github.com/lesonky/google-maps-mcp/issues
Author-email: Lesonky <lesonky@gmail.com>
License: MIT
Keywords: ai,claude,fastmcp,google-maps,mcp
Classifier: Development Status :: 4 - Beta
Classifier: Intended Audience :: Developers
Classifier: License :: OSI Approved :: MIT License
Classifier: Programming Language :: Python :: 3
Classifier: Programming Language :: Python :: 3.10
Classifier: Programming Language :: Python :: 3.11
Classifier: Programming Language :: Python :: 3.12
Classifier: Programming Language :: Python :: 3.13
Requires-Python: >=3.10
Requires-Dist: fastmcp>=2.0.0
Requires-Dist: httpx>=0.27.0
Requires-Dist: pydantic>=2.0.0
Provides-Extra: dev
Requires-Dist: black>=23.0; extra == 'dev'
Requires-Dist: mypy>=1.0; extra == 'dev'
Requires-Dist: pytest-asyncio>=0.21.0; extra == 'dev'
Requires-Dist: pytest>=7.0; extra == 'dev'
Requires-Dist: ruff>=0.1.0; extra == 'dev'
